[{"season":2026,"player":"Enrique Hernández","team":"LAD","pa":4,"wrc_plus":801.912,"woba":1.365,"war":0.306},{"season":2026,"player":"Rafael Flores Jr.","team":"PIT","pa":5,"wrc_plus":515.518,"woba":0.941,"war":0.255},{"season":2026,"player":"Luke Williams","team":"ATL","pa":1,"wrc_plus":354.904,"woba":0.7,"war":0.034},{"season":2026,"player":"Jair Camargo","team":"ATL","pa":2,"wrc_plus":308.664,"woba":0.631,"war":0.045},{"season":2026,"player":"Gabriel Gonzalez","team":"MIN","pa":4,"wrc_plus":276.651,"woba":0.572,"war":0.083},{"season":2026,"player":"Justin Dean","team":"CHC","pa":6,"wrc_plus":243.989,"woba":0.531,"war":0.099},{"season":2026,"player":"Luis Urías","team":"TOR","pa":18,"wrc_plus":226.836,"woba":0.498,"war":0.384},{"season":2026,"player":"LaMonte Wade Jr.","team":"HOU","pa":13,"wrc_plus":209.873,"woba":0.474,"war":0.132},{"season":2026,"player":"Will Wilson","team":"SEA","pa":6,"wrc_plus":204.714,"woba":0.458,"war":0.104},{"season":2026,"player":"Esmerlyn Valdez","team":"PIT","pa":69,"wrc_plus":199.157,"woba":0.469,"war":1.122},{"season":2026,"player":"Logan Porter","team":"- - -","pa":6,"wrc_plus":187.185,"woba":0.443,"war":0.086},{"season":2026,"player":"Yordan Alvarez","team":"HOU","pa":383,"wrc_plus":186.826,"woba":0.44,"war":3.996},{"season":2026,"player":"Tommy Edman","team":"LAD","pa":52,"wrc_plus":183.502,"woba":0.442,"war":0.547},{"season":2026,"player":"Juan Soto","team":"NYM","pa":294,"wrc_plus":164.945,"woba":0.411,"war":2.735},{"season":2026,"player":"Ryan Jeffers","team":"MIN","pa":147,"wrc_plus":164.584,"woba":0.41,"war":1.728},{"season":2026,"player":"Luis Campusano","team":"SDP","pa":58,"wrc_plus":163.354,"woba":0.408,"war":0.817},{"season":2026,"player":"Andrew Vaughn","team":"MIL","pa":149,"wrc_plus":161.403,"woba":0.409,"war":1.285},{"season":2026,"player":"Nick Kurtz","team":"ATH","pa":394,"wrc_plus":160.922,"woba":0.408,"war":3.53},{"season":2026,"player":"Joshua Kuroda-Grauer","team":"ATH","pa":15,"wrc_plus":159.556,"woba":0.406,"war":0.182},{"season":2026,"player":"Munetaka Murakami","team":"CHW","pa":246,"wrc_plus":156.05,"woba":0.397,"war":1.994},{"season":2026,"player":"Ben Rice","team":"NYY","pa":351,"wrc_plus":154.961,"woba":0.393,"war":2.406},{"season":2026,"player":"Junior Caminero","team":"TBR","pa":372,"wrc_plus":154.627,"woba":0.396,"war":3.002},{"season":2026,"player":"Nelson Velázquez","team":"STL","pa":50,"wrc_plus":154.229,"woba":0.396,"war":0.142},{"season":2026,"player":"Joey Wiemer","team":"WSN","pa":83,"wrc_plus":152.577,"woba":0.397,"war":0.841},{"season":2026,"player":"Yandy Díaz","team":"TBR","pa":360,"wrc_plus":152.433,"woba":0.392,"war":2.554},{"season":2026,"player":"Shohei Ohtani","team":"LAD","pa":377,"wrc_plus":151.072,"woba":0.394,"war":2.787},{"season":2026,"player":"John Rave","team":"KCR","pa":21,"wrc_plus":150.839,"woba":0.393,"war":0.217},{"season":2026,"player":"Kyle Schwarber","team":"PHI","pa":375,"wrc_plus":150.819,"woba":0.397,"war":2.457},{"season":2026,"player":"Willson Contreras","team":"BOS","pa":347,"wrc_plus":149.588,"woba":0.393,"war":2.795},{"season":2026,"player":"Aaron Judge","team":"NYY","pa":261,"wrc_plus":149.529,"woba":0.385,"war":2.14},{"season":2026,"player":"Dominic Canzone","team":"SEA","pa":227,"wrc_plus":149.014,"woba":0.377,"war":1.492},{"season":2026,"player":"James Wood","team":"WSN","pa":416,"wrc_plus":148.763,"woba":0.391,"war":3.32},{"season":2026,"player":"Pete Crow-Armstrong","team":"CHC","pa":381,"wrc_plus":147.556,"woba":0.387,"war":5.233},{"season":2026,"player":"Anthony Seigler","team":"BOS","pa":49,"wrc_plus":145.433,"woba":0.387,"war":0.498},{"season":2026,"player":"Brendan Donovan","team":"SEA","pa":101,"wrc_plus":145.169,"woba":0.371,"war":0.586},{"season":2026,"player":"Byron Buxton","team":"MIN","pa":329,"wrc_plus":144.435,"woba":0.381,"war":2.88},{"season":2026,"player":"Bryce Harper","team":"PHI","pa":369,"wrc_plus":143.8,"woba":0.386,"war":1.858},{"season":2026,"player":"Freddie Freeman","team":"LAD","pa":376,"wrc_plus":143.041,"woba":0.382,"war":2.817},{"season":2026,"player":"Jordan Lawlar","team":"ARI","pa":44,"wrc_plus":142.471,"woba":0.384,"war":0.501},{"season":2026,"player":"Endy Rodríguez","team":"PIT","pa":118,"wrc_plus":142.058,"woba":0.384,"war":0.961},{"season":2026,"player":"Mickey Moniak","team":"COL","pa":203,"wrc_plus":141.321,"woba":0.4,"war":1.562},{"season":2026,"player":"Mike Trout","team":"LAA","pa":335,"wrc_plus":140.396,"woba":0.376,"war":2.458},{"season":2026,"player":"Max Muncy","team":"LAD","pa":312,"wrc_plus":140.226,"woba":0.378,"war":3.211},{"season":2026,"player":"Bryan Reynolds","team":"PIT","pa":387,"wrc_plus":139.097,"woba":0.38,"war":2.47},{"season":2026,"player":"Jonathan Aranda","team":"TBR","pa":367,"wrc_plus":138.454,"woba":0.372,"war":2.138},{"season":2026,"player":"Jordan Walker","team":"STL","pa":356,"wrc_plus":138.388,"woba":0.373,"war":2.225},{"season":2026,"player":"Victor Bericoto","team":"SFG","pa":44,"wrc_plus":138.236,"woba":0.372,"war":0.111},{"season":2026,"player":"Miguel Vargas","team":"CHW","pa":374,"wrc_plus":137.875,"woba":0.37,"war":3.153},{"season":2026,"player":"Matt Olson","team":"ATL","pa":374,"wrc_plus":137.851,"woba":0.376,"war":2.796},{"season":2026,"player":"Samad Taylor","team":"SDP","pa":96,"wrc_plus":137.33,"woba":0.369,"war":0.699},{"season":2026,"player":"Jake Bauers","team":"MIL","pa":307,"wrc_plus":137.282,"woba":0.373,"war":1.535},{"season":2026,"player":"Elias Díaz","team":"- - -","pa":73,"wrc_plus":137.192,"woba":0.369,"war":0.677},{"season":2026,"player":"Paul Goldschmidt","team":"NYY","pa":237,"wrc_plus":136.453,"woba":0.366,"war":1.73},{"season":2026,"player":"Jackson Chourio","team":"MIL","pa":244,"wrc_plus":136.102,"woba":0.372,"war":1.992},{"season":2026,"player":"Dillon Dingler","team":"DET","pa":339,"wrc_plus":135.906,"woba":0.368,"war":4.01},{"season":2026,"player":"Lars Nootbaar","team":"STL","pa":93,"wrc_plus":135.766,"woba":0.369,"war":0.777},{"season":2026,"player":"Randy Arozarena","team":"SEA","pa":343,"wrc_plus":135.453,"woba":0.357,"war":2.34},{"season":2026,"player":"Kevin McGonigle","team":"DET","pa":378,"wrc_plus":135.208,"woba":0.367,"war":3.634},{"season":2026,"player":"Luis García Jr.","team":"WSN","pa":286,"wrc_plus":135.134,"woba":0.371,"war":1.558},{"season":2026,"player":"CJ Abrams","team":"WSN","pa":359,"wrc_plus":134.819,"woba":0.371,"war":2.476},{"season":2026,"player":"Brandon Marsh","team":"PHI","pa":328,"wrc_plus":134.741,"woba":0.373,"war":1.86},{"season":2026,"player":"Otto Lopez","team":"MIA","pa":372,"wrc_plus":134.526,"woba":0.372,"war":3.835},{"season":2026,"player":"Corbin Carroll","team":"ARI","pa":359,"wrc_plus":134.499,"woba":0.372,"war":3.356},{"season":2026,"player":"Junior Perez","team":"CHW","pa":18,"wrc_plus":134.141,"woba":0.365,"war":0.105},{"season":2026,"player":"Justin Foscue","team":"TEX","pa":105,"wrc_plus":133.762,"woba":0.362,"war":0.861},{"season":2026,"player":"Spencer Horwitz","team":"PIT","pa":295,"wrc_plus":133.133,"woba":0.371,"war":1.349},{"season":2026,"player":"José Azócar","team":"ATL","pa":16,"wrc_plus":132.836,"woba":0.368,"war":0.233},{"season":2026,"player":"Sam Antonacci","team":"CHW","pa":276,"wrc_plus":132.784,"woba":0.363,"war":1.525},{"season":2026,"player":"Tyler Black","team":"MIL","pa":28,"wrc_plus":131.252,"woba":0.364,"war":0.13},{"season":2026,"player":"Bryce Eldridge","team":"SFG","pa":180,"wrc_plus":130.998,"woba":0.361,"war":0.668},{"season":2026,"player":"Dalton Rushing","team":"LAD","pa":184,"wrc_plus":130.679,"woba":0.364,"war":1.101},{"season":2026,"player":"Riley Greene","team":"DET","pa":367,"wrc_plus":130.668,"woba":0.36,"war":2.136},{"season":2026,"player":"Bryan Torres","team":"STL","pa":55,"wrc_plus":130.655,"woba":0.361,"war":0.522},{"season":2026,"player":"Josh Jung","team":"TEX","pa":355,"wrc_plus":130.237,"woba":0.357,"war":2.51},{"season":2026,"player":"Iván Herrera","team":"STL","pa":384,"wrc_plus":130.109,"woba":0.36,"war":1.731},{"season":2026,"player":"Randal Grichuk","team":"- - -","pa":126,"wrc_plus":130.097,"woba":0.359,"war":0.439},{"season":2026,"player":"Griffin Conine","team":"MIA","pa":66,"wrc_plus":129.516,"woba":0.365,"war":0.48},{"season":2026,"player":"Cole Carrigg","team":"COL","pa":87,"wrc_plus":129.501,"woba":0.383,"war":0.711},{"season":2026,"player":"Trevor Larnach","team":"MIN","pa":265,"wrc_plus":129.313,"woba":0.359,"war":1.558},{"season":2026,"player":"Zack Gelof","team":"ATH","pa":228,"wrc_plus":128.916,"woba":0.361,"war":1.862},{"season":2026,"player":"Wyatt Langford","team":"TEX","pa":173,"wrc_plus":128.873,"woba":0.355,"war":1.555},{"season":2026,"player":"Donovan Walton","team":"LAA","pa":93,"wrc_plus":128.09,"woba":0.358,"war":0.258},{"season":2026,"player":"Garrett Mitchell","team":"MIL","pa":272,"wrc_plus":128.041,"woba":0.359,"war":1.848},{"season":2026,"player":"Bobby Witt Jr.","team":"KCR","pa":362,"wrc_plus":127.996,"woba":0.36,"war":4.621},{"season":2026,"player":"Jose Siri","team":"LAA","pa":85,"wrc_plus":127.594,"woba":0.357,"war":0.73},{"season":2026,"player":"Gary Sánchez","team":"MIL","pa":162,"wrc_plus":127.552,"woba":0.359,"war":0.62},{"season":2026,"player":"Gleyber Torres","team":"DET","pa":190,"wrc_plus":127.142,"woba":0.355,"war":0.959},{"season":2026,"player":"Ryan Vilade","team":"TBR","pa":144,"wrc_plus":126.981,"woba":0.356,"war":0.653},{"season":2026,"player":"Ryan Kreidler","team":"MIN","pa":120,"wrc_plus":126.381,"woba":0.355,"war":0.743},{"season":2026,"player":"Jeremy Peña","team":"HOU","pa":202,"wrc_plus":125.761,"woba":0.352,"war":1.779},{"season":2026,"player":"Luis Arraez","team":"SFG","pa":361,"wrc_plus":125.603,"woba":0.353,"war":3.376},{"season":2026,"player":"Michael Stefanic","team":"ATH","pa":5,"wrc_plus":125.505,"woba":0.356,"war":0.047},{"season":2026,"player":"Seiya Suzuki","team":"CHC","pa":309,"wrc_plus":125.498,"woba":0.354,"war":1.8},{"season":2026,"player":"Ty France","team":"SDP","pa":204,"wrc_plus":125.47,"woba":0.351,"war":1.228},{"season":2026,"player":"Liam Hicks","team":"MIA","pa":308,"wrc_plus":125.455,"woba":0.359,"war":1.618},{"season":2026,"player":"Esteury Ruiz","team":"MIA","pa":101,"wrc_plus":125.26,"woba":0.358,"war":0.794},{"season":2026,"player":"Joc Pederson","team":"TEX","pa":268,"wrc_plus":125.239,"woba":0.35,"war":0.822},{"season":2026,"player":"Brice Turang","team":"MIL","pa":374,"wrc_plus":124.514,"woba":0.354,"war":2.973},{"season":2026,"player":"TJ Rumfield","team":"COL","pa":350,"wrc_plus":124.449,"woba":0.375,"war":1.496},{"season":2026,"player":"Michael Harris II","team":"ATL","pa":309,"wrc_plus":124.441,"woba":0.356,"war":2.138},{"season":2026,"player":"Michael Conforto","team":"CHC","pa":144,"wrc_plus":124.386,"woba":0.352,"war":0.511},{"season":2026,"player":"Alec Burleson","team":"STL","pa":363,"wrc_plus":124.216,"woba":0.352,"war":1.815},{"season":2026,"player":"Oneil Cruz","team":"PIT","pa":283,"wrc_plus":124.086,"woba":0.357,"war":1.602},{"season":2026,"player":"Pete Alonso","team":"BAL","pa":384,"wrc_plus":123.84,"woba":0.348,"war":1.72},{"season":2026,"player":"Shea Langeliers","team":"ATH","pa":363,"wrc_plus":123.573,"woba":0.354,"war":2.188},{"season":2026,"player":"Gabriel Moreno","team":"ARI","pa":237,"wrc_plus":123.294,"woba":0.355,"war":1.837},{"season":2026,"player":"Blaze Alexander","team":"BAL","pa":218,"wrc_plus":123.21,"woba":0.347,"war":1.143},{"season":2026,"player":"Jung Hoo Lee","team":"SFG","pa":317,"wrc_plus":123.087,"woba":0.35,"war":1.415},{"season":2026,"player":"Max Schuemann","team":"NYY","pa":48,"wrc_plus":122.658,"woba":0.346,"war":0.373},{"season":2026,"player":"Carlos Correa","team":"HOU","pa":141,"wrc_plus":122.63,"woba":0.347,"war":1.115},{"season":2026,"player":"JJ Bleday","team":"CIN","pa":250,"wrc_plus":121.739,"woba":0.358,"war":1.08},{"season":2026,"player":"Jake McCarthy","team":"COL","pa":269,"wrc_plus":121.726,"woba":0.371,"war":1.525},{"season":2026,"player":"Elly De La Cruz","team":"CIN","pa":303,"wrc_plus":121.712,"woba":0.358,"war":2.537},{"season":2026,"player":"Tyler Callihan","team":"PIT","pa":69,"wrc_plus":121.623,"woba":0.354,"war":0.249},{"season":2026,"player":"Jeferson Quero","team":"MIL","pa":2,"wrc_plus":121.551,"woba":0.35,"war":0.021},{"season":2026,"player":"Xavier Edwards","team":"MIA","pa":372,"wrc_plus":121.483,"woba":0.353,"war":2.617},{"season":2026,"player":"Jac Caglianone","team":"KCR","pa":309,"wrc_plus":121.371,"woba":0.351,"war":1.452},{"season":2026,"player":"Ronald Acuña Jr.","team":"ATL","pa":236,"wrc_plus":121.2,"woba":0.351,"war":0.87},{"season":2026,"player":"Alika Williams","team":"ATH","pa":77,"wrc_plus":121.118,"woba":0.35,"war":0.421},{"season":2026,"player":"Cody Bellinger","team":"NYY","pa":365,"wrc_plus":120.304,"woba":0.343,"war":2.552},{"season":2026,"player":"Gavin Sheets","team":"SDP","pa":284,"wrc_plus":120.067,"woba":0.343,"war":0.932},{"season":2026,"player":"Andy Pages","team":"LAD","pa":381,"wrc_plus":119.963,"woba":0.348,"war":2.878},{"season":2026,"player":"Carlos Cortes","team":"ATH","pa":213,"wrc_plus":119.898,"woba":0.348,"war":0.343},{"season":2026,"player":"Ketel Marte","team":"ARI","pa":365,"wrc_plus":119.573,"woba":0.349,"war":2.135},{"season":2026,"player":"Tyler Soderstrom","team":"ATH","pa":335,"wrc_plus":119.202,"woba":0.347,"war":1.383},{"season":2026,"player":"Brandon Lowe","team":"PIT","pa":366,"wrc_plus":118.968,"woba":0.35,"war":2.556},{"season":2026,"player":"Kazuma Okamoto","team":"TOR","pa":348,"wrc_plus":118.388,"woba":0.341,"war":2.018},{"season":2026,"player":"Nicky Lopez","team":"- - -","pa":105,"wrc_plus":118.377,"woba":0.338,"war":0.573},{"season":2026,"player":"Connor Wong","team":"BOS","pa":114,"wrc_plus":118.18,"woba":0.348,"war":0.598},{"season":2026,"player":"Kerry Carpenter","team":"DET","pa":210,"wrc_plus":117.914,"woba":0.342,"war":0.13},{"season":2026,"player":"Curtis Mead","team":"WSN","pa":262,"wrc_plus":117.838,"woba":0.345,"war":0.725},{"season":2026,"player":"Tristan Peters","team":"CHW","pa":252,"wrc_plus":117.827,"woba":0.341,"war":2.277},{"season":2026,"player":"Michael Busch","team":"CHC","pa":390,"wrc_plus":117.684,"woba":0.342,"war":1.848},{"season":2026,"player":"Kody Clemens","team":"MIN","pa":296,"wrc_plus":117.355,"woba":0.342,"war":1.469},{"season":2026,"player":"Nathaniel Lowe","team":"CIN","pa":211,"wrc_plus":117.293,"woba":0.352,"war":0.315},{"season":2026,"player":"Samuel Basallo","team":"BAL","pa":271,"wrc_plus":117.164,"woba":0.338,"war":1.116},{"season":2026,"player":"Isaac Paredes","team":"HOU","pa":348,"wrc_plus":117.071,"woba":0.339,"war":1.774},{"season":2026,"player":"Casey Schmitt","team":"SFG","pa":330,"wrc_plus":117.038,"woba":0.341,"war":1.375},{"season":2026,"player":"Trent Grisham","team":"NYY","pa":268,"wrc_plus":116.786,"woba":0.338,"war":1.025},{"season":2026,"player":"Luke Raley","team":"SEA","pa":233,"wrc_plus":116.761,"woba":0.33,"war":0.508},{"season":2026,"player":"Travis Bazzana","team":"CLE","pa":245,"wrc_plus":116.654,"woba":0.338,"war":1.426},{"season":2026,"player":"Troy Johnston","team":"COL","pa":293,"wrc_plus":116.501,"woba":0.364,"war":0.789},{"season":2026,"player":"Ryan O'Hearn","team":"PIT","pa":305,"wrc_plus":116.207,"woba":0.346,"war":0.574},{"season":2026,"player":"Carson Kelly","team":"CHC","pa":227,"wrc_plus":116.054,"woba":0.34,"war":0.919},{"season":2026,"player":"Hunter Goodman","team":"COL","pa":344,"wrc_plus":115.809,"woba":0.362,"war":1.821},{"season":2026,"player":"Romy Gonzalez","team":"BOS","pa":15,"wrc_plus":115.502,"woba":0.344,"war":0.048},{"season":2026,"player":"Julio Rodríguez","team":"SEA","pa":378,"wrc_plus":115.157,"woba":0.328,"war":1.934},{"season":2026,"player":"Wade Meckler","team":"LAA","pa":123,"wrc_plus":114.727,"woba":0.338,"war":0.792},{"season":2026,"player":"Taylor Ward","team":"BAL","pa":404,"wrc_plus":114.646,"woba":0.334,"war":1.206},{"season":2026,"player":"William Contreras","team":"MIL","pa":355,"wrc_plus":114.585,"woba":0.339,"war":1.949},{"season":2026,"player":"Adley Rutschman","team":"BAL","pa":244,"wrc_plus":114.393,"woba":0.334,"war":2.057},{"season":2026,"player":"Drake Baldwin","team":"ATL","pa":279,"wrc_plus":114.362,"woba":0.341,"war":1.225},{"season":2026,"player":"JJ Wetherholt","team":"STL","pa":370,"wrc_plus":114.349,"woba":0.337,"war":3.334},{"season":2026,"player":"Ian Happ","team":"CHC","pa":365,"wrc_plus":114.265,"woba":0.337,"war":1.714},{"season":2026,"player":"Sal Stewart","team":"CIN","pa":378,"wrc_plus":114.264,"woba":0.347,"war":1.539},{"season":2026,"player":"Zach Neto","team":"LAA","pa":387,"wrc_plus":113.989,"woba":0.337,"war":1.671},{"season":2026,"player":"Will Wagner","team":"SDP","pa":45,"wrc_plus":113.744,"woba":0.334,"war":-0.072},{"season":2026,"player":"Christian Walker","team":"HOU","pa":365,"wrc_plus":113.563,"woba":0.334,"war":1.3},{"season":2026,"player":"Colson Montgomery","team":"CHW","pa":346,"wrc_plus":113.463,"woba":0.335,"war":2.36},{"season":2026,"player":"Henry Bolte","team":"ATH","pa":174,"wrc_plus":113.373,"woba":0.339,"war":1.17},{"season":2026,"player":"Kyle Stowers","team":"MIA","pa":277,"wrc_plus":113.3,"woba":0.34,"war":1.15},{"season":2026,"player":"Teoscar Hernández","team":"LAD","pa":223,"wrc_plus":112.901,"woba":0.337,"war":0.998},{"season":2026,"player":"Amed Rosario","team":"NYY","pa":153,"wrc_plus":112.506,"woba":0.332,"war":0.268},{"season":2026,"player":"Brandon Nimmo","team":"TEX","pa":354,"wrc_plus":111.951,"woba":0.33,"war":1.249},{"season":2026,"player":"Nathan Lukes","team":"TOR","pa":188,"wrc_plus":111.885,"woba":0.332,"war":0.934},{"season":2026,"player":"Rafael Devers","team":"SFG","pa":367,"wrc_plus":111.717,"woba":0.333,"war":0.854},{"season":2026,"player":"Chase DeLauter","team":"CLE","pa":297,"wrc_plus":111.524,"woba":0.33,"war":0.973},{"season":2026,"player":"Jonah Heim","team":"- - -","pa":152,"wrc_plus":111.437,"woba":0.336,"war":0.886},{"season":2026,"player":"Miguel Rojas","team":"LAD","pa":145,"wrc_plus":111.118,"woba":0.335,"war":0.839},{"season":2026,"player":"A.J. Ewing","team":"NYM","pa":184,"wrc_plus":110.78,"woba":0.33,"war":0.816},{"season":2026,"player":"Brandon Valenzuela","team":"TOR","pa":172,"wrc_plus":110.538,"woba":0.33,"war":1.688},{"season":2026,"player":"Ceddanne Rafaela","team":"BOS","pa":329,"wrc_plus":110.292,"woba":0.336,"war":2.704},{"season":2026,"player":"José Ramírez","team":"CLE","pa":314,"wrc_plus":110.267,"woba":0.328,"war":2.33},{"season":2026,"player":"Keibert Ruiz","team":"WSN","pa":194,"wrc_plus":109.722,"woba":0.333,"war":1.337},{"season":2026,"player":"Brayan Rocchio","team":"CLE","pa":328,"wrc_plus":109.39,"woba":0.327,"war":2.662},{"season":2026,"player":"Miguel Amaya","team":"CHC","pa":144,"wrc_plus":108.77,"woba":0.329,"war":0.869},{"season":2026,"player":"Ernie Clement","team":"TOR","pa":339,"wrc_plus":108.723,"woba":0.327,"war":1.074},{"season":2026,"player":"Ezequiel Duran","team":"TEX","pa":294,"wrc_plus":108.183,"woba":0.325,"war":2.009},{"season":2026,"player":"Taylor Trammell","team":"HOU","pa":112,"wrc_plus":108.145,"woba":0.326,"war":0.34},{"season":2026,"player":"Heliot Ramos","team":"SFG","pa":195,"wrc_plus":107.859,"woba":0.327,"war":0.51},{"season":2026,"player":"Nick Gonzales","team":"PIT","pa":338,"wrc_plus":107.745,"woba":0.333,"war":1.347},{"season":2026,"player":"Wilyer Abreu","team":"BOS","pa":363,"wrc_plus":107.572,"woba":0.332,"war":1.854},{"season":2026,"player":"Jesús Sánchez","team":"TOR","pa":234,"wrc_plus":107.498,"woba":0.325,"war":0.071},{"season":2026,"player":"Rowdy Tellez","team":"ATL","pa":11,"wrc_plus":107.431,"woba":0.33,"war":0.029},{"season":2026,"player":"Ozzie Albies","team":"ATL","pa":369,"wrc_plus":107.382,"woba":0.33,"war":1.764},{"season":2026,"player":"Kyle Tucker","team":"LAD","pa":353,"wrc_plus":107.208,"woba":0.329,"war":1.046},{"season":2026,"player":"Carter Jensen","team":"KCR","pa":312,"wrc_plus":107.031,"woba":0.33,"war":1.53},{"season":2026,"player":"Francisco Alvarez","team":"NYM","pa":208,"wrc_plus":106.994,"woba":0.324,"war":0.872},{"season":2026,"player":"Jonah Cox","team":"SFG","pa":29,"wrc_plus":106.934,"woba":0.326,"war":0.242},{"season":2026,"player":"Alex Call","team":"LAD","pa":126,"wrc_plus":106.741,"woba":0.328,"war":0.559},{"season":2026,"player":"Spencer Torkelson","team":"DET","pa":339,"wrc_plus":106.562,"woba":0.325,"war":0.37},{"season":2026,"player":"Jacob Gonzalez","team":"CHW","pa":92,"wrc_plus":106.332,"woba":0.325,"war":0.435},{"season":2026,"player":"Chase Meidroth","team":"CHW","pa":359,"wrc_plus":105.986,"woba":0.324,"war":1.647},{"season":2026,"player":"Jake Burger","team":"TEX","pa":345,"wrc_plus":105.897,"woba":0.322,"war":1.072},{"season":2026,"player":"Braden Montgomery","team":"CHW","pa":88,"wrc_plus":105.648,"woba":0.324,"war":0.579},{"season":2026,"player":"Daulton Varsho","team":"TOR","pa":279,"wrc_plus":105.496,"woba":0.322,"war":1.344},{"season":2026,"player":"Matt Shaw","team":"CHC","pa":147,"wrc_plus":105.463,"woba":0.324,"war":0.494},{"season":2026,"player":"J.P. Crawford","team":"SEA","pa":300,"wrc_plus":105.461,"woba":0.314,"war":0.72},{"season":2026,"player":"Cole Young","team":"SEA","pa":354,"wrc_plus":105.45,"woba":0.314,"war":1.52},{"season":2026,"player":"Dane Myers","team":"CIN","pa":137,"wrc_plus":105.431,"woba":0.334,"war":0.442},{"season":2026,"player":"David Fry","team":"CLE","pa":141,"wrc_plus":104.796,"woba":0.32,"war":0.219},{"season":2026,"player":"Mauricio Dubón","team":"ATL","pa":331,"wrc_plus":104.59,"woba":0.326,"war":1.701},{"season":2026,"player":"Brandon Lockridge","team":"MIL","pa":96,"wrc_plus":104.045,"woba":0.324,"war":0.307},{"season":2026,"player":"Austin Hedges","team":"CLE","pa":135,"wrc_plus":104.039,"woba":0.319,"war":0.596},{"season":2026,"player":"Kyle Karros","team":"COL","pa":284,"wrc_plus":104.001,"woba":0.345,"war":1.637},{"season":2026,"player":"Colt Emerson","team":"SEA","pa":138,"wrc_plus":103.878,"woba":0.311,"war":0.546},{"season":2026,"player":"Javier Sanoja","team":"MIA","pa":215,"wrc_plus":103.452,"woba":0.326,"war":0.839},{"season":2026,"player":"Brooks Lee","team":"MIN","pa":338,"wrc_plus":103.181,"woba":0.321,"war":1.1},{"season":2026,"player":"Yohendrick Piñango","team":"TOR","pa":155,"wrc_plus":103.032,"woba":0.319,"war":0.05},{"season":2026,"player":"Fernando Tatis Jr.","team":"SDP","pa":377,"wrc_plus":102.98,"woba":0.318,"war":1.523},{"season":2026,"player":"Nick Madrigal","team":"LAA","pa":52,"wrc_plus":102.735,"woba":0.321,"war":0.3},{"season":2026,"player":"Alex Jackson","team":"MIN","pa":47,"wrc_plus":102.582,"woba":0.32,"war":-0.002},{"season":2026,"player":"Sean Keys","team":"TOR","pa":16,"wrc_plus":102.535,"woba":0.318,"war":0.024},{"season":2026,"player":"Will Smith","team":"LAD","pa":201,"wrc_plus":102.397,"woba":0.322,"war":1.014},{"season":2026,"player":"Mookie Betts","team":"LAD","pa":232,"wrc_plus":102.389,"woba":0.322,"war":1.34},{"season":2026,"player":"Jonny DeLuca","team":"TBR","pa":157,"wrc_plus":102.314,"woba":0.32,"war":0.869},{"season":2026,"player":"Jake Mangum","team":"PIT","pa":221,"wrc_plus":102.246,"woba":0.325,"war":0.802},{"season":2026,"player":"Carson Benge","team":"NYM","pa":347,"wrc_plus":102.054,"woba":0.317,"war":1.356},{"season":2026,"player":"José Fermín","team":"STL","pa":141,"wrc_plus":102.015,"woba":0.319,"war":0.289},{"season":2026,"player":"Jhonny Pereda","team":"SEA","pa":68,"wrc_plus":102.013,"woba":0.308,"war":0.293},{"season":2026,"player":"Giancarlo Stanton","team":"NYY","pa":96,"wrc_plus":101.937,"woba":0.316,"war":0.074},{"season":2026,"player":"Konnor Griffin","team":"PIT","pa":237,"wrc_plus":101.858,"woba":0.324,"war":1.076},{"season":2026,"player":"Nick Sogard","team":"BOS","pa":41,"wrc_plus":101.8,"woba":0.324,"war":0.248},{"season":2026,"player":"Ben Malgeri","team":"DET","pa":15,"wrc_plus":101.715,"woba":0.318,"war":0.05},{"season":2026,"player":"Kyle Manzardo","team":"CLE","pa":279,"wrc_plus":100.699,"woba":0.314,"war":0.188},{"season":2026,"player":"Ryan Ward","team":"LAD","pa":60,"wrc_plus":100.592,"woba":0.319,"war":0.258},{"season":2026,"player":"Nolan Schanuel","team":"LAA","pa":294,"wrc_plus":100.323,"woba":0.317,"war":0.725},{"season":2026,"player":"Geraldo Perdomo","team":"ARI","pa":355,"wrc_plus":100.256,"woba":0.321,"war":1.873},{"season":2026,"player":"Joe Mack","team":"MIA","pa":150,"wrc_plus":100.117,"woba":0.321,"war":1.197},{"season":2026,"player":"Dansby Swanson","team":"CHC","pa":326,"wrc_plus":100.047,"woba":0.316,"war":2.406},{"season":2026,"player":"Raynel Delgado","team":"HOU","pa":33,"wrc_plus":99.797,"woba":0.314,"war":-0.163},{"season":2026,"player":"Gunnar Henderson","team":"BAL","pa":403,"wrc_plus":99.524,"woba":0.312,"war":2.108},{"season":2026,"player":"Miguel Andujar","team":"SDP","pa":224,"wrc_plus":99.405,"woba":0.312,"war":-0.067},{"season":2026,"player":"Josh Rojas","team":"KCR","pa":16,"wrc_plus":98.872,"woba":0.318,"war":-0.005},{"season":2026,"player":"Daylen Lile","team":"WSN","pa":372,"wrc_plus":98.796,"woba":0.317,"war":1.22},{"season":2026,"player":"Everson Pereira","team":"CHW","pa":77,"wrc_plus":98.706,"woba":0.314,"war":0.264},{"season":2026,"player":"Nathan Church","team":"STL","pa":225,"wrc_plus":98.598,"woba":0.314,"war":0.705},{"season":2026,"player":"Victor Caratini","team":"MIN","pa":247,"wrc_plus":98.596,"woba":0.314,"war":0.943},{"season":2026,"player":"Andrew Benintendi","team":"CHW","pa":271,"wrc_plus":98.555,"woba":0.314,"war":-0.019},{"season":2026,"player":"Owen Caissie","team":"MIA","pa":241,"wrc_plus":98.234,"woba":0.318,"war":-0.214},{"season":2026,"player":"Leody Taveras","team":"BAL","pa":269,"wrc_plus":97.997,"woba":0.31,"war":0.8},{"season":2026,"player":"Angel Martínez","team":"CLE","pa":243,"wrc_plus":97.715,"woba":0.31,"war":0.956},{"season":2026,"player":"Anthony Volpe","team":"NYY","pa":140,"wrc_plus":97.526,"woba":0.31,"war":1.063},{"season":2026,"player":"Jorge Soler","team":"LAA","pa":280,"wrc_plus":97.473,"woba":0.313,"war":-0.148},{"season":2026,"player":"Vladimir Guerrero Jr.","team":"TOR","pa":352,"wrc_plus":97.444,"woba":0.311,"war":0.849},{"season":2026,"player":"Christian Yelich","team":"MIL","pa":234,"wrc_plus":97.359,"woba":0.314,"war":0.146},{"season":2026,"player":"Isiah Kiner-Falefa","team":"BOS","pa":132,"wrc_plus":97.274,"woba":0.317,"war":1.109},{"season":2026,"player":"Denzer Guzman","team":"LAA","pa":85,"wrc_plus":97.142,"woba":0.313,"war":0.288},{"season":2026,"player":"Ryan Mountcastle","team":"BAL","pa":15,"wrc_plus":97.09,"woba":0.309,"war":-0.005},{"season":2026,"player":"Dominic Smith","team":"ATL","pa":211,"wrc_plus":96.547,"woba":0.314,"war":-0.045},{"season":2026,"player":"Alex Bregman","team":"CHC","pa":395,"wrc_plus":96.491,"woba":0.311,"war":1.448},{"season":2026,"player":"Spencer Steer","team":"CIN","pa":325,"wrc_plus":96.483,"woba":0.321,"war":0.4},{"season":2026,"player":"Blake Dunn","team":"CIN","pa":155,"wrc_plus":96.425,"woba":0.321,"war":0.594},{"season":2026,"player":"Jazz Chisholm Jr.","team":"NYY","pa":330,"wrc_plus":96.399,"woba":0.308,"war":2.135},{"season":2026,"player":"Derek Hill","team":"- - -","pa":125,"wrc_plus":96.204,"woba":0.312,"war":0.414},{"season":2026,"player":"Spencer Jones","team":"NYY","pa":82,"wrc_plus":95.946,"woba":0.308,"war":0.094},{"season":2026,"player":"Stuart Fairchild","team":"CLE","pa":27,"wrc_plus":95.801,"woba":0.307,"war":0.036},{"season":2026,"player":"Matt Chapman","team":"SFG","pa":352,"wrc_plus":95.772,"woba":0.309,"war":1.331},{"season":2026,"player":"Josh Bell","team":"MIN","pa":340,"wrc_plus":95.755,"woba":0.31,"war":0.042},{"season":2026,"player":"Nick Loftin","team":"KCR","pa":174,"wrc_plus":95.704,"woba":0.313,"war":-0.137},{"season":2026,"player":"Josh Naylor","team":"SEA","pa":355,"wrc_plus":95.225,"woba":0.299,"war":0.18},{"season":2026,"player":"Eric Wagaman","team":"NYM","pa":29,"wrc_plus":95.151,"woba":0.307,"war":-0.068},{"season":2026,"player":"Colton Cowser","team":"BAL","pa":217,"wrc_plus":94.735,"woba":0.306,"war":1.028},{"season":2026,"player":"Nolan Arenado","team":"ARI","pa":315,"wrc_plus":94.709,"woba":0.312,"war":1.133},{"season":2026,"player":"Jared Young","team":"NYM","pa":131,"wrc_plus":94.414,"woba":0.306,"war":0.375},{"season":2026,"player":"Pedro Ramírez","team":"CHC","pa":58,"wrc_plus":94.374,"woba":0.308,"war":0.161},{"season":2026,"player":"Sung-Mun Song","team":"SDP","pa":72,"wrc_plus":94.147,"woba":0.304,"war":0.321},{"season":2026,"player":"Kahlil Watson","team":"CLE","pa":50,"wrc_plus":94.088,"woba":0.305,"war":0.139},{"season":2026,"player":"Rhys Hoskins","team":"CLE","pa":249,"wrc_plus":93.852,"woba":0.305,"war":-0.472},{"season":2026,"player":"Jesus Rodriguez","team":"SFG","pa":43,"wrc_plus":93.784,"woba":0.306,"war":-0.192},{"season":2026,"player":"Austin Martin","team":"MIN","pa":257,"wrc_plus":93.659,"woba":0.307,"war":0.582},{"season":2026,"player":"Isaac Collins","team":"KCR","pa":285,"wrc_plus":93.654,"woba":0.31,"war":-0.045},{"season":2026,"player":"Heriberto Hernández","team":"MIA","pa":199,"wrc_plus":93.522,"woba":0.311,"war":0.315},{"season":2026,"player":"José Caballero","team":"NYY","pa":271,"wrc_plus":93.518,"woba":0.304,"war":0.941},{"season":2026,"player":"George Springer","team":"TOR","pa":279,"wrc_plus":92.854,"woba":0.304,"war":0.045},{"season":2026,"player":"Max Muncy","team":"ATH","pa":167,"wrc_plus":92.711,"woba":0.309,"war":-0.121},{"season":2026,"player":"Vaughn Grissom","team":"LAA","pa":188,"wrc_plus":92.287,"woba":0.306,"war":0.219},{"season":2026,"player":"Roman Anthony","team":"BOS","pa":130,"wrc_plus":92.219,"woba":0.31,"war":0.302},{"season":2026,"player":"Michael Massey","team":"KCR","pa":218,"wrc_plus":92.15,"woba":0.308,"war":1.133},{"season":2026,"player":"MJ Melendez","team":"NYM","pa":144,"wrc_plus":92.134,"woba":0.302,"war":0.088},{"season":2026,"player":"Jake Fraley","team":"TBR","pa":90,"wrc_plus":91.855,"woba":0.305,"war":0.117},{"season":2026,"player":"Jorbit Vivas","team":"WSN","pa":188,"wrc_plus":91.78,"woba":0.306,"war":0.488},{"season":2026,"player":"Luke Keaschall","team":"MIN","pa":324,"wrc_plus":91.723,"woba":0.304,"war":0.668},{"season":2026,"player":"Ildemaro Vargas","team":"ARI","pa":274,"wrc_plus":91.682,"woba":0.308,"war":0.479},{"season":2026,"player":"Trey Mancini","team":"LAA","pa":14,"wrc_plus":91.61,"woba":0.305,"war":-0.008},{"season":2026,"player":"Moisés Ballesteros","team":"CHC","pa":175,"wrc_plus":91.546,"woba":0.304,"war":-0.043},{"season":2026,"player":"Maikel Garcia","team":"KCR","pa":294,"wrc_plus":91.409,"woba":0.307,"war":1.423},{"season":2026,"player":"Hao-Yu  Lee","team":"DET","pa":145,"wrc_plus":91.259,"woba":0.303,"war":-0.032},{"season":2026,"player":"Mitch Garver","team":"SEA","pa":120,"wrc_plus":91.236,"woba":0.293,"war":0.29},{"season":2026,"player":"Willy Adames","team":"SFG","pa":345,"wrc_plus":91.192,"woba":0.302,"war":-0.068},{"season":2026,"player":"Willi Castro","team":"COL","pa":293,"wrc_plus":91.09,"woba":0.326,"war":0.38},{"season":2026,"player":"Deyvison De Los Santos","team":"MIA","pa":7,"wrc_plus":91.086,"woba":0.307,"war":0.019},{"season":2026,"player":"Luis Robert Jr.","team":"NYM","pa":98,"wrc_plus":90.97,"woba":0.3,"war":0.113},{"season":2026,"player":"Jacob Wilson","team":"ATH","pa":214,"wrc_plus":90.872,"woba":0.306,"war":1.168},{"season":2026,"player":"Masyn Winn","team":"STL","pa":323,"wrc_plus":90.821,"woba":0.302,"war":1.662},{"season":2026,"player":"Xander Bogaerts","team":"SDP","pa":329,"wrc_plus":90.699,"woba":0.299,"war":1.401},{"season":2026,"player":"Masataka Yoshida","team":"BOS","pa":181,"wrc_plus":90.561,"woba":0.308,"war":-0.162},{"season":2026,"player":"Cam Smith","team":"HOU","pa":332,"wrc_plus":90.546,"woba":0.301,"war":1.347},{"season":2026,"player":"Francisco Lindor","team":"NYM","pa":135,"wrc_plus":90.476,"woba":0.3,"war":0.584},{"season":2026,"player":"Jorge Mateo","team":"ATL","pa":122,"wrc_plus":90.267,"woba":0.305,"war":0.682},{"season":2026,"player":"Bo Bichette","team":"NYM","pa":383,"wrc_plus":90.167,"woba":0.299,"war":1.078},{"season":2026,"player":"Oswald Peraza","team":"LAA","pa":258,"wrc_plus":89.896,"woba":0.302,"war":0.886},{"season":2026,"player":"Tyler Freeman","team":"COL","pa":224,"wrc_plus":89.709,"woba":0.324,"war":-0.158},{"season":2026,"player":"Bryson Stott","team":"PHI","pa":315,"wrc_plus":89.6,"woba":0.306,"war":1.307},{"season":2026,"player":"Alejandro Osuna","team":"TEX","pa":173,"wrc_plus":89.042,"woba":0.297,"war":-0.297},{"season":2026,"player":"Jose Altuve","team":"HOU","pa":282,"wrc_plus":89.019,"woba":0.298,"war":0.176},{"season":2026,"player":"Manny Machado","team":"SDP","pa":357,"wrc_plus":88.275,"woba":0.296,"war":1.011},{"season":2026,"player":"Colt Keith","team":"DET","pa":251,"wrc_plus":87.909,"woba":0.298,"war":0.459},{"season":2026,"player":"Drew Gilbert","team":"SFG","pa":193,"wrc_plus":86.603,"woba":0.295,"war":0.067},{"season":2026,"player":"Corey Seager","team":"TEX","pa":219,"wrc_plus":86.488,"woba":0.294,"war":0.616},{"season":2026,"player":"Omar Martinez","team":"LAA","pa":3,"wrc_plus":86.208,"woba":0.297,"war":-0.044},{"season":2026,"player":"Brady House","team":"WSN","pa":177,"wrc_plus":86.044,"woba":0.298,"war":-0.165},{"season":2026,"player":"Caleb Durbin","team":"BOS","pa":282,"wrc_plus":86.015,"woba":0.301,"war":1.116},{"season":2026,"player":"Nico Hoerner","team":"CHC","pa":389,"wrc_plus":85.998,"woba":0.295,"war":1.468},{"season":2026,"player":"Dylan Beavers","team":"BAL","pa":134,"wrc_plus":85.916,"woba":0.293,"war":-0.164},{"season":2026,"player":"Ryan Waldschmidt","team":"ARI","pa":122,"wrc_plus":85.889,"woba":0.299,"war":0.439},{"season":2026,"player":"Ramón Laureano","team":"SDP","pa":206,"wrc_plus":85.67,"woba":0.292,"war":0.226},{"season":2026,"player":"Lane Thomas","team":"KCR","pa":231,"wrc_plus":85.457,"woba":0.299,"war":0.214},{"season":2026,"player":"Tyler Stephenson","team":"CIN","pa":237,"wrc_plus":85.394,"woba":0.304,"war":0.083},{"season":2026,"player":"Royce Lewis","team":"MIN","pa":222,"wrc_plus":85.118,"woba":0.295,"war":0.207},{"season":2026,"player":"Javier Báez","team":"DET","pa":82,"wrc_plus":85.102,"woba":0.294,"war":-0.012},{"season":2026,"player":"Jo Adell","team":"LAA","pa":369,"wrc_plus":84.494,"woba":0.294,"war":-0.081},{"season":2026,"player":"Andrés Chaparro","team":"WSN","pa":58,"wrc_plus":84.188,"woba":0.295,"war":0.032},{"season":2026,"player":"Dustin Harris","team":"- - -","pa":52,"wrc_plus":84.11,"woba":0.292,"war":0.166},{"season":2026,"player":"Tommy Troy","team":"ARI","pa":113,"wrc_plus":83.859,"woba":0.296,"war":0.114},{"season":2026,"player":"Andrés Giménez","team":"TOR","pa":293,"wrc_plus":83.529,"woba":0.29,"war":1.599},{"season":2026,"player":"Sal Frelick","team":"MIL","pa":284,"wrc_plus":83.484,"woba":0.293,"war":-0.003},{"season":2026,"player":"Agustín Ramírez","team":"MIA","pa":129,"wrc_plus":83.386,"woba":0.296,"war":-0.013},{"season":2026,"player":"David Hamilton","team":"MIL","pa":232,"wrc_plus":83.359,"woba":0.293,"war":0.348},{"season":2026,"player":"José Tena","team":"WSN","pa":169,"wrc_plus":83.332,"woba":0.294,"war":-0.21},{"season":2026,"player":"Hyeseong Kim","team":"LAD","pa":131,"wrc_plus":83.234,"woba":0.293,"war":0.357},{"season":2026,"player":"CJ Kayfus","team":"CLE","pa":25,"wrc_plus":82.912,"woba":0.289,"war":-0.184},{"season":2026,"player":"Joey Loperfido","team":"HOU","pa":120,"wrc_plus":82.853,"woba":0.29,"war":0.212},{"season":2026,"player":"Taylor Walls","team":"TBR","pa":240,"wrc_plus":82.736,"woba":0.292,"war":0.595},{"season":2026,"player":"Jackson Holliday","team":"BAL","pa":121,"wrc_plus":82.568,"woba":0.288,"war":0.183},{"season":2026,"player":"Eloy Jiménez","team":"TOR","pa":35,"wrc_plus":82.552,"woba":0.289,"war":-0.093},{"season":2026,"player":"Myles Straw","team":"TOR","pa":152,"wrc_plus":82.235,"woba":0.289,"war":0.299},{"season":2026,"player":"Kyle Higashioka","team":"TEX","pa":164,"wrc_plus":82.186,"woba":0.287,"war":0.084},{"season":2026,"player":"Evan Carter","team":"TEX","pa":241,"wrc_plus":82.021,"woba":0.287,"war":1.054},{"season":2026,"player":"Nick Fortes","team":"TBR","pa":207,"wrc_plus":82,"woba":0.29,"war":0.387},{"season":2026,"player":"Kyle Teel","team":"CHW","pa":39,"wrc_plus":81.979,"woba":0.29,"war":0.039},{"season":2026,"player":"Jeremiah Jackson","team":"BAL","pa":206,"wrc_plus":81.975,"woba":0.287,"war":0.161},{"season":2026,"player":"Orlando Arcia","team":"MIN","pa":50,"wrc_plus":81.907,"woba":0.29,"war":0.058},{"season":2026,"player":"Starling Marte","team":"KCR","pa":112,"wrc_plus":81.862,"woba":0.293,"war":-0.006},{"season":2026,"player":"Ben Williamson","team":"TBR","pa":202,"wrc_plus":81.758,"woba":0.29,"war":0.294},{"season":2026,"player":"Brent Rooker","team":"ATH","pa":203,"wrc_plus":81.695,"woba":0.293,"war":-0.146},{"season":2026,"player":"Josh Smith","team":"TEX","pa":121,"wrc_plus":81.505,"woba":0.286,"war":0.009},{"season":2026,"player":"Chandler Simpson","team":"TBR","pa":324,"wrc_plus":81.279,"woba":0.289,"war":1.016},{"season":2026,"player":"Vinnie Pasquantino","team":"KCR","pa":291,"wrc_plus":81.276,"woba":0.292,"war":-0.104},{"season":2026,"player":"Connor Norby","team":"MIA","pa":233,"wrc_plus":81.263,"woba":0.293,"war":0.179},{"season":2026,"player":"Richie Palacios","team":"TBR","pa":203,"wrc_plus":81.129,"woba":0.289,"war":-0.144},{"season":2026,"player":"Parker Meadows","team":"DET","pa":39,"wrc_plus":80.778,"woba":0.288,"war":0.227},{"season":2026,"player":"Hunter Feduccia","team":"TBR","pa":120,"wrc_plus":80.637,"woba":0.288,"war":0.159},{"season":2026,"player":"Cedric Mullins","team":"TBR","pa":289,"wrc_plus":80.511,"woba":0.288,"war":0.669},{"season":2026,"player":"Braden Shewmake","team":"HOU","pa":79,"wrc_plus":80.311,"woba":0.286,"war":0.025},{"season":2026,"player":"Daniel Susac","team":"SFG","pa":115,"wrc_plus":80.101,"woba":0.286,"war":0.719},{"season":2026,"player":"Jonathan India","team":"KCR","pa":58,"wrc_plus":80.066,"woba":0.291,"war":-0.048},{"season":2026,"player":"Jace Jung","team":"DET","pa":8,"wrc_plus":79.758,"woba":0.286,"war":-0.025},{"season":2026,"player":"Ryan McMahon","team":"NYY","pa":205,"wrc_plus":79.535,"woba":0.284,"war":0.62},{"season":2026,"player":"Sterlin Thompson","team":"COL","pa":77,"wrc_plus":79.431,"woba":0.308,"war":-0.206},{"season":2026,"player":"Kyle Isbel","team":"KCR","pa":183,"wrc_plus":79.397,"woba":0.29,"war":0.449},{"season":2026,"player":"Mike Yastrzemski","team":"ATL","pa":238,"wrc_plus":79.199,"woba":0.288,"war":-0.079},{"season":2026,"player":"Dylan Crews","team":"WSN","pa":159,"wrc_plus":79.145,"woba":0.288,"war":0.319},{"season":2026,"player":"Jacob Young","team":"WSN","pa":277,"wrc_plus":78.461,"woba":0.287,"war":1.182},{"season":2026,"player":"Trea Turner","team":"PHI","pa":380,"wrc_plus":78.199,"woba":0.289,"war":0.352},{"season":2026,"player":"Connor Joe","team":"SEA","pa":45,"wrc_plus":78.153,"woba":0.274,"war":-0.175},{"season":2026,"player":"Justin Crawford","team":"PHI","pa":268,"wrc_plus":77.891,"woba":0.288,"war":-0.002},{"season":2026,"player":"Adam Frazier","team":"LAA","pa":93,"wrc_plus":77.55,"woba":0.284,"war":-0.014},{"season":2026,"player":"Daniel Schneemann","team":"CLE","pa":242,"wrc_plus":77.277,"woba":0.28,"war":0.812},{"season":2026,"player":"Colby Thomas","team":"ATH","pa":93,"wrc_plus":77.234,"woba":0.286,"war":-0.235},{"season":2026,"player":"Alex Freeland","team":"LAD","pa":207,"wrc_plus":76.788,"woba":0.283,"war":0.481},{"season":2026,"player":"Eric Haase","team":"SFG","pa":73,"wrc_plus":76.732,"woba":0.28,"war":-0.075},{"season":2026,"player":"Travis d'Arnaud","team":"LAA","pa":40,"wrc_plus":76.588,"woba":0.283,"war":0.066},{"season":2026,"player":"Jackson Merrill","team":"SDP","pa":354,"wrc_plus":76.299,"woba":0.278,"war":0.772},{"season":2026,"player":"Will Benson","team":"CIN","pa":114,"wrc_plus":76.234,"woba":0.29,"war":-0.178},{"season":2026,"player":"Jared Triolo","team":"PIT","pa":188,"wrc_plus":76.105,"woba":0.286,"war":0.182},{"season":2026,"player":"Nasim Nuñez","team":"WSN","pa":288,"wrc_plus":75.851,"woba":0.283,"war":0.889},{"season":2026,"player":"Ali Sánchez","team":"NYY","pa":27,"wrc_plus":75.718,"woba":0.278,"war":0.194},{"season":2026,"player":"Jose Fernandez","team":"ARI","pa":177,"wrc_plus":75.596,"woba":0.284,"war":-0.112},{"season":2026,"player":"Yoán Moncada","team":"LAA","pa":130,"wrc_plus":75.567,"woba":0.282,"war":-0.3},{"season":2026,"player":"Santiago Espinal","team":"LAD","pa":60,"wrc_plus":75.535,"woba":0.282,"war":0.057},{"season":2026,"player":"Steven Kwan","team":"CLE","pa":328,"wrc_plus":75.524,"woba":0.278,"war":0.606},{"season":2026,"player":"Nate Eaton","team":"BOS","pa":34,"wrc_plus":75.467,"woba":0.286,"war":0.018},{"season":2026,"player":"Weston Wilson","team":"- - -","pa":59,"wrc_plus":75.169,"woba":0.275,"war":-0.319},{"season":2026,"player":"Coby Mayo","team":"BAL","pa":234,"wrc_plus":74.353,"woba":0.276,"war":-0.14},{"season":2026,"player":"Logan O'Hoppe","team":"LAA","pa":208,"wrc_plus":74.223,"woba":0.28,"war":-0.343},{"season":2026,"player":"Jakob Marsee","team":"MIA","pa":360,"wrc_plus":74.187,"woba":0.282,"war":0.053},{"season":2026,"player":"Edouard Julien","team":"COL","pa":234,"wrc_plus":73.942,"woba":0.3,"war":-0.521},{"season":2026,"player":"Alec Bohm","team":"PHI","pa":334,"wrc_plus":73.745,"woba":0.282,"war":-0.19},{"season":2026,"player":"Matt McLain","team":"CIN","pa":303,"wrc_plus":73.373,"woba":0.286,"war":0.192},{"season":2026,"player":"Darell Hernaiz","team":"ATH","pa":134,"wrc_plus":73.241,"woba":0.28,"war":0.345},{"season":2026,"player":"Jarred Kelenic","team":"- - -","pa":69,"wrc_plus":73.218,"woba":0.276,"war":-0.147},{"season":2026,"player":"Jasson Domínguez","team":"NYY","pa":104,"wrc_plus":73.181,"woba":0.275,"war":-0.05},{"season":2026,"player":"Eugenio Suárez","team":"CIN","pa":234,"wrc_plus":72.561,"woba":0.285,"war":-0.8},{"season":2026,"player":"Mark Vientos","team":"NYM","pa":245,"wrc_plus":72.34,"woba":0.273,"war":-1.153},{"season":2026,"player":"Marcus Semien","team":"NYM","pa":318,"wrc_plus":71.674,"woba":0.272,"war":-0.346},{"season":2026,"player":"Austin Riley","team":"ATL","pa":347,"wrc_plus":71.437,"woba":0.277,"war":-0.192},{"season":2026,"player":"Ramón Urías","team":"STL","pa":68,"wrc_plus":71.372,"woba":0.273,"war":-0.265},{"season":2026,"player":"Edmundo Sosa","team":"PHI","pa":145,"wrc_plus":71.274,"woba":0.278,"war":0.026},{"season":2026,"player":"Brett Baty","team":"NYM","pa":290,"wrc_plus":70.796,"woba":0.27,"war":-0.358},{"season":2026,"player":"Tyler O'Neill","team":"BAL","pa":159,"wrc_plus":70.143,"woba":0.27,"war":-0.248},{"season":2026,"player":"Blaze Jordan","team":"STL","pa":68,"wrc_plus":70.13,"woba":0.271,"war":0.053},{"season":2026,"player":"Joey Bart","team":"- - -","pa":79,"wrc_plus":70.061,"woba":0.276,"war":0.029},{"season":2026,"player":"Pedro Pagés","team":"STL","pa":149,"wrc_plus":69.775,"woba":0.27,"war":0.588},{"season":2026,"player":"Mickey Gasper","team":"BOS","pa":119,"wrc_plus":69.73,"woba":0.278,"war":-0.304},{"season":2026,"player":"Luis Torrens","team":"NYM","pa":161,"wrc_plus":69.467,"woba":0.268,"war":0.894},{"season":2026,"player":"Austin Slater","team":"- - -","pa":74,"wrc_plus":69.125,"woba":0.271,"war":0.002},{"season":2026,"player":"Danny Jansen","team":"TEX","pa":142,"wrc_plus":69.122,"woba":0.268,"war":-0.254},{"season":2026,"player":"Marcell Ozuna","team":"PIT","pa":238,"wrc_plus":68.56,"woba":0.275,"war":-0.805},{"season":2026,"player":"J.T. Realmuto","team":"PHI","pa":231,"wrc_plus":68.517,"woba":0.274,"war":0.505},{"season":2026,"player":"Andruw Monasterio","team":"BOS","pa":145,"wrc_plus":67.937,"woba":0.275,"war":-0.835},{"season":2026,"player":"Jeff McNeil","team":"ATH","pa":281,"wrc_plus":67.909,"woba":0.273,"war":-0.454},{"season":2026,"player":"Davis Schneider","team":"TOR","pa":118,"wrc_plus":67.533,"woba":0.267,"war":-0.386},{"season":2026,"player":"Noelvi Marte","team":"CIN","pa":117,"wrc_plus":67.403,"woba":0.277,"war":-0.409},{"season":2026,"player":"Christian Vázquez","team":"HOU","pa":178,"wrc_plus":67.151,"woba":0.267,"war":-0.095},{"season":2026,"player":"Josh Lowe","team":"LAA","pa":159,"wrc_plus":67.107,"woba":0.269,"war":-0.018},{"season":2026,"player":"Eli White","team":"ATL","pa":115,"wrc_plus":66.935,"woba":0.27,"war":0.219},{"season":2026,"player":"Nolan Gorman","team":"STL","pa":229,"wrc_plus":66.792,"woba":0.266,"war":-0.261},{"season":2026,"player":"Victor Mesa Jr.","team":"TBR","pa":82,"wrc_plus":66.563,"woba":0.268,"war":0.028},{"season":2026,"player":"Yainer Diaz","team":"HOU","pa":153,"wrc_plus":66.071,"woba":0.265,"war":-0.384},{"season":2026,"player":"Cal Raleigh","team":"SEA","pa":246,"wrc_plus":66.007,"woba":0.256,"war":0.463},{"season":2026,"player":"Nick Allen","team":"HOU","pa":82,"wrc_plus":65.895,"woba":0.265,"war":0.206},{"season":2026,"player":"Jorge Barrosa","team":"ARI","pa":124,"wrc_plus":65.545,"woba":0.269,"war":0.138},{"season":2026,"player":"Zach Dezenzo","team":"HOU","pa":51,"wrc_plus":65.088,"woba":0.264,"war":-0.137},{"season":2026,"player":"Lawrence Butler","team":"ATH","pa":245,"wrc_plus":65.051,"woba":0.269,"war":-1.029},{"season":2026,"player":"Gabriel Arias","team":"CLE","pa":76,"wrc_plus":64.636,"woba":0.262,"war":0.145},{"season":2026,"player":"Tristan Gray","team":"MIN","pa":173,"wrc_plus":64.543,"woba":0.265,"war":-0.349},{"season":2026,"player":"Adolis García","team":"PHI","pa":259,"wrc_plus":64.468,"woba":0.268,"war":0.032},{"season":2026,"player":"Victor Robles","team":"SEA","pa":80,"wrc_plus":64.253,"woba":0.254,"war":0.042},{"season":2026,"player":"Wenceel Pérez","team":"DET","pa":175,"wrc_plus":63.216,"woba":0.262,"war":-0.438},{"season":2026,"player":"Marcelo Mayer","team":"BOS","pa":228,"wrc_plus":62.588,"woba":0.267,"war":-0.124},{"season":2026,"player":"Jake Meyers","team":"HOU","pa":148,"wrc_plus":61.915,"woba":0.259,"war":-0.097},{"season":2026,"player":"Jake Cronenworth","team":"SDP","pa":132,"wrc_plus":61.696,"woba":0.256,"war":-0.187},{"season":2026,"player":"Zach McKinstry","team":"DET","pa":217,"wrc_plus":61.646,"woba":0.26,"war":0.166},{"season":2026,"player":"Kyle Farmer","team":"ATL","pa":15,"wrc_plus":61.646,"woba":0.262,"war":-0.034},{"season":2026,"player":"Braxton Fulford","team":"COL","pa":54,"wrc_plus":61.634,"woba":0.282,"war":-0.087},{"season":2026,"player":"Alejandro Kirk","team":"TOR","pa":77,"wrc_plus":59.828,"woba":0.256,"war":0.224},{"season":2026,"player":"Jarren Duran","team":"BOS","pa":343,"wrc_plus":59.479,"woba":0.263,"war":-0.016},{"season":2026,"player":"Sebastián Rivero","team":"LAA","pa":57,"wrc_plus":59.004,"woba":0.258,"war":0.124},{"season":2026,"player":"Tanner Murray","team":"CHW","pa":33,"wrc_plus":58.753,"woba":0.256,"war":-0.063},{"season":2026,"player":"Matt Vierling","team":"DET","pa":239,"wrc_plus":58.382,"woba":0.255,"war":-0.591},{"season":2026,"player":"Brett Sullivan","team":"COL","pa":124,"wrc_plus":58.32,"woba":0.277,"war":-0.396},{"season":2026,"player":"Drew Millas","team":"WSN","pa":140,"wrc_plus":58.185,"woba":0.256,"war":0.016},{"season":2026,"player":"Lourdes Gurriel Jr.","team":"ARI","pa":158,"wrc_plus":57.782,"woba":0.257,"war":-0.579},{"season":2026,"player":"Edwin Arroyo","team":"CIN","pa":86,"wrc_plus":57.566,"woba":0.263,"war":-0.035},{"season":2026,"player":"Matt Wallner","team":"MIN","pa":135,"wrc_plus":56.516,"woba":0.253,"war":-0.837},{"season":2026,"player":"Nick Yorke","team":"PIT","pa":86,"wrc_plus":55.822,"woba":0.256,"war":-0.151},{"season":2026,"player":"Andrew McCutchen","team":"TEX","pa":83,"wrc_plus":55.717,"woba":0.249,"war":-0.448},{"season":2026,"player":"Brice Matthews","team":"HOU","pa":211,"wrc_plus":55.559,"woba":0.25,"war":-0.04},{"season":2026,"player":"Leo Jiménez","team":"MIA","pa":109,"wrc_plus":55.067,"woba":0.254,"war":-0.507},{"season":2026,"player":"Henry Davis","team":"PIT","pa":167,"wrc_plus":55.05,"woba":0.254,"war":0.031},{"season":2026,"player":"Cooper Pratt","team":"MIL","pa":56,"wrc_plus":54.825,"woba":0.25,"war":0.119},{"season":2026,"player":"Victor Scott II","team":"STL","pa":184,"wrc_plus":54.748,"woba":0.248,"war":-0.228},{"season":2026,"player":"Joey Ortiz","team":"MIL","pa":206,"wrc_plus":53.721,"woba":0.249,"war":0.144},{"season":2026,"player":"Cam Cauley","team":"TEX","pa":13,"wrc_plus":52.984,"woba":0.245,"war":-0.07},{"season":2026,"player":"Tim Tawa","team":"ARI","pa":76,"wrc_plus":51.66,"woba":0.248,"war":-0.344},{"season":2026,"player":"James Outman","team":"- - -","pa":116,"wrc_plus":51.593,"woba":0.246,"war":-0.172},{"season":2026,"player":"Luis Rengifo","team":"MIL","pa":209,"wrc_plus":51.412,"woba":0.245,"war":-0.674},{"season":2026,"player":"Rodolfo Durán","team":"SDP","pa":82,"wrc_plus":51.224,"woba":0.24,"war":0.189},{"season":2026,"player":"Salvador Perez","team":"KCR","pa":340,"wrc_plus":51.132,"woba":0.249,"war":-1.597},{"season":2026,"player":"Tyrone Taylor","team":"NYM","pa":111,"wrc_plus":50.904,"woba":0.241,"war":-0.632},{"season":2026,"player":"Jorge Polanco","team":"NYM","pa":61,"wrc_plus":50.805,"woba":0.24,"war":-0.348},{"season":2026,"player":"Freddy Fermin","team":"SDP","pa":162,"wrc_plus":50.706,"woba":0.24,"war":0.106},{"season":2026,"player":"Alek Thomas","team":"ARI","pa":100,"wrc_plus":50.184,"woba":0.246,"war":-0.091},{"season":2026,"player":"Nick Castellanos","team":"SDP","pa":122,"wrc_plus":49.928,"woba":0.239,"war":-0.843},{"season":2026,"player":"LuJames Groover","team":"ARI","pa":54,"wrc_plus":49.819,"woba":0.245,"war":-0.144},{"season":2026,"player":"Austin Hays","team":"CHW","pa":44,"wrc_plus":49.68,"woba":0.243,"war":-0.353},{"season":2026,"player":"Kevin Alcántara","team":"CHC","pa":14,"wrc_plus":49.544,"woba":0.241,"war":-0.204},{"season":2026,"player":"Jimmy Crooks","team":"STL","pa":62,"wrc_plus":49.222,"woba":0.24,"war":-0.168},{"season":2026,"player":"Michael Helman","team":"TEX","pa":35,"wrc_plus":49.126,"woba":0.239,"war":-0.179},{"season":2026,"player":"Kameron Misner","team":"KCR","pa":38,"wrc_plus":48.939,"woba":0.246,"war":-0.296},{"season":2026,"player":"Drew Romo","team":"CHW","pa":111,"wrc_plus":48.868,"woba":0.242,"war":0.08},{"season":2026,"player":"Harrison Bader","team":"SFG","pa":111,"wrc_plus":48.456,"woba":0.238,"war":-0.435},{"season":2026,"player":"Jose Trevino","team":"CIN","pa":59,"wrc_plus":48.195,"woba":0.249,"war":0.121},{"season":2026,"player":"Carlos Narváez","team":"BOS","pa":162,"wrc_plus":48.018,"woba":0.246,"war":0.172},{"season":2026,"player":"Drew Cavanaugh","team":"SFG","pa":18,"wrc_plus":47.434,"woba":0.237,"war":-0.134},{"season":2026,"player":"Ezequiel Tovar","team":"COL","pa":311,"wrc_plus":47.401,"woba":0.26,"war":-0.39},{"season":2026,"player":"Cody Freeman","team":"TEX","pa":18,"wrc_plus":47.359,"woba":0.237,"war":-0.102},{"season":2026,"player":"Shay Whitcomb","team":"HOU","pa":24,"wrc_plus":46.436,"woba":0.237,"war":-0.099},{"season":2026,"player":"George Valera","team":"CLE","pa":38,"wrc_plus":46.005,"woba":0.235,"war":-0.36},{"season":2026,"player":"Thomas Saggese","team":"STL","pa":82,"wrc_plus":45.946,"woba":0.235,"war":-0.387},{"season":2026,"player":"P.J. Higgins","team":"CIN","pa":32,"wrc_plus":45.936,"woba":0.245,"war":-0.04},{"season":2026,"player":"Adrian Del Castillo","team":"ARI","pa":161,"wrc_plus":45.828,"woba":0.239,"war":-0.773},{"season":2026,"player":"TJ Friedl","team":"CIN","pa":192,"wrc_plus":45.753,"woba":0.245,"war":-0.606},{"season":2026,"player":"Nick Solak","team":"SDP","pa":10,"wrc_plus":45.578,"woba":0.232,"war":-0.068},{"season":2026,"player":"Trevor Story","team":"BOS","pa":176,"wrc_plus":45.567,"woba":0.242,"war":-0.472},{"season":2026,"player":"Blake Perkins","team":"MIL","pa":101,"wrc_plus":45.081,"woba":0.236,"war":-0.558},{"season":2026,"player":"Miles Mastrobuoni","team":"SEA","pa":27,"wrc_plus":44.475,"woba":0.225,"war":-0.201},{"season":2026,"player":"Zach Cole","team":"HOU","pa":53,"wrc_plus":44.417,"woba":0.234,"war":-0.148},{"season":2026,"player":"Juan Brito","team":"CLE","pa":56,"wrc_plus":44.241,"woba":0.233,"war":-0.313},{"season":2026,"player":"Brett Harris","team":"ATH","pa":6,"wrc_plus":44.111,"woba":0.238,"war":-0.009},{"season":2026,"player":"Bryce Teodosio","team":"LAA","pa":51,"wrc_plus":43.452,"woba":0.235,"war":0.06},{"season":2026,"player":"Zack Short","team":"- - -","pa":55,"wrc_plus":42.612,"woba":0.233,"war":-0.151},{"season":2026,"player":"Brenton Doyle","team":"COL","pa":122,"wrc_plus":42.149,"woba":0.253,"war":-0.564},{"season":2026,"player":"Luisangel Acuña","team":"CHW","pa":150,"wrc_plus":41.935,"woba":0.231,"war":-0.567},{"season":2026,"player":"Daniel Johnson","team":"HOU","pa":17,"wrc_plus":41.856,"woba":0.23,"war":-0.102},{"season":2026,"player":"Gage Workman","team":"DET","pa":38,"wrc_plus":41.426,"woba":0.231,"war":-0.428},{"season":2026,"player":"J.C. Escarra","team":"NYY","pa":92,"wrc_plus":41.213,"woba":0.228,"war":0.152},{"season":2026,"player":"Yohel Pozo","team":"STL","pa":33,"wrc_plus":40.723,"woba":0.227,"war":-0.171},{"season":2026,"player":"Leo Rivas","team":"SEA","pa":120,"wrc_plus":39.474,"woba":0.218,"war":-0.206},{"season":2026,"player":"Chadwick Tromp","team":"- - -","pa":30,"wrc_plus":38.56,"woba":0.228,"war":-0.113},{"season":2026,"player":"Graham Pauley","team":"MIA","pa":97,"wrc_plus":37.679,"woba":0.228,"war":-0.282},{"season":2026,"player":"Scott Kingery","team":"CHC","pa":4,"wrc_plus":37.372,"woba":0.223,"war":-0.13},{"season":2026,"player":"Austin Wells","team":"NYY","pa":197,"wrc_plus":37.359,"woba":0.223,"war":-0.351},{"season":2026,"player":"Edgar Quero","team":"CHW","pa":172,"wrc_plus":37.35,"woba":0.225,"war":-0.724},{"season":2026,"player":"Patrick Bailey","team":"- - -","pa":176,"wrc_plus":37.161,"woba":0.221,"war":-0.09},{"season":2026,"player":"Pavin Smith","team":"ARI","pa":77,"wrc_plus":37.06,"woba":0.226,"war":-0.553},{"season":2026,"player":"Tyler Tolbert","team":"KCR","pa":41,"wrc_plus":35.314,"woba":0.226,"war":-0.161},{"season":2026,"player":"Reese McGuire","team":"CHW","pa":34,"wrc_plus":35.201,"woba":0.222,"war":-0.256},{"season":2026,"player":"Collin Price","team":"HOU","pa":13,"wrc_plus":34.464,"woba":0.219,"war":-0.022},{"season":2026,"player":"Rikuu Nishida","team":"CHW","pa":30,"wrc_plus":30.645,"woba":0.215,"war":-0.141},{"season":2026,"player":"Lenyn Sosa","team":"- - -","pa":117,"wrc_plus":30.247,"woba":0.214,"war":-0.759},{"season":2026,"player":"Jhostynxon Garcia","team":"PIT","pa":37,"wrc_plus":30.034,"woba":0.217,"war":-0.301},{"season":2026,"player":"Jordan Beck","team":"COL","pa":88,"wrc_plus":29.491,"woba":0.234,"war":-0.666},{"season":2026,"player":"Bryce Johnson","team":"SDP","pa":49,"wrc_plus":29.179,"woba":0.208,"war":-0.116},{"season":2026,"player":"Jake Rogers","team":"DET","pa":86,"wrc_plus":28.601,"woba":0.212,"war":-0.366},{"season":2026,"player":"Joey Meneses","team":"ATH","pa":18,"wrc_plus":28.424,"woba":0.216,"war":-0.295},{"season":2026,"player":"Jahmai Jones","team":"DET","pa":103,"wrc_plus":27.153,"woba":0.21,"war":-1.101},{"season":2026,"player":"James McCann","team":"ARI","pa":62,"wrc_plus":24.989,"woba":0.208,"war":-0.407},{"season":2026,"player":"Rob Refsnyder","team":"SEA","pa":119,"wrc_plus":23.775,"woba":0.195,"war":-1.072},{"season":2026,"player":"Luis Matos","team":"MIL","pa":21,"wrc_plus":23.123,"woba":0.203,"war":-0.037},{"season":2026,"player":"Tyler Heineman","team":"- - -","pa":100,"wrc_plus":23.047,"woba":0.204,"war":0.102},{"season":2026,"player":"Garrett Stubbs","team":"PHI","pa":28,"wrc_plus":21.736,"woba":0.204,"war":-0.044},{"season":2026,"player":"Bo Naylor","team":"CLE","pa":90,"wrc_plus":21.253,"woba":0.199,"war":-0.552},{"season":2026,"player":"Hayden Senger","team":"NYM","pa":17,"wrc_plus":20.779,"woba":0.196,"war":-0.142},{"season":2026,"player":"Aramis Garcia","team":"ARI","pa":19,"wrc_plus":20.346,"woba":0.201,"war":-0.104},{"season":2026,"player":"Jim Jarvis","team":"ATL","pa":9,"wrc_plus":18.537,"woba":0.198,"war":-0.147},{"season":2026,"player":"Ronny Mauricio","team":"NYM","pa":45,"wrc_plus":18.44,"woba":0.192,"war":-0.511},{"season":2026,"player":"Jeimer Candelario","team":"LAA","pa":20,"wrc_plus":17.698,"woba":0.198,"war":-0.407},{"season":2026,"player":"Christopher Morel","team":"MIA","pa":73,"wrc_plus":17.558,"woba":0.198,"war":-0.797},{"season":2026,"player":"Johnathan Rodríguez","team":"BAL","pa":11,"wrc_plus":15.64,"woba":0.191,"war":-0.195},{"season":2026,"player":"Denzel Clarke","team":"ATH","pa":60,"wrc_plus":15.096,"woba":0.196,"war":-0.286},{"season":2026,"player":"Christian Moore","team":"LAA","pa":22,"wrc_plus":15.049,"woba":0.194,"war":-0.387},{"season":2026,"player":"Charles McAdoo","team":"TOR","pa":25,"wrc_plus":13.365,"woba":0.189,"war":-0.233},{"season":2026,"player":"Sam Huff","team":"BAL","pa":23,"wrc_plus":13.124,"woba":0.187,"war":-0.027},{"season":2026,"player":"Gabriel Rincones Jr.","team":"PHI","pa":46,"wrc_plus":12.788,"woba":0.191,"war":-0.421},{"season":2026,"player":"Sam Haggerty","team":"TEX","pa":47,"wrc_plus":12.212,"woba":0.186,"war":-0.24},{"season":2026,"player":"Jerar Encarnacion","team":"SFG","pa":35,"wrc_plus":11.524,"woba":0.183,"war":-0.451},{"season":2026,"player":"Ke'Bryan Hayes","team":"CIN","pa":128,"wrc_plus":9.742,"woba":0.191,"war":-0.878},{"season":2026,"player":"Petey Halpin","team":"CLE","pa":56,"wrc_plus":8.851,"woba":0.181,"war":-0.101},{"season":2026,"player":"Patrick Wisdom","team":"SEA","pa":44,"wrc_plus":7.549,"woba":0.172,"war":-0.434},{"season":2026,"player":"Felix Reyes","team":"PHI","pa":38,"wrc_plus":5.887,"woba":0.181,"war":-0.382},{"season":2026,"player":"Cooper Ingle","team":"CLE","pa":17,"wrc_plus":5.08,"woba":0.176,"war":-0.339},{"season":2026,"player":"Luken Baker","team":"ARI","pa":5,"wrc_plus":4.753,"woba":0.178,"war":-0.054},{"season":2026,"player":"Addison Barger","team":"TOR","pa":28,"wrc_plus":0.429,"woba":0.17,"war":-0.043},{"season":2026,"player":"César Salazar","team":"HOU","pa":22,"wrc_plus":-0.203,"woba":0.169,"war":-0.14},{"season":2026,"player":"Ryan Bliss","team":"SEA","pa":10,"wrc_plus":-1.103,"woba":0.159,"war":-0.087},{"season":2026,"player":"Rece Hinds","team":"CIN","pa":36,"wrc_plus":-4.875,"woba":0.17,"war":-0.336},{"season":2026,"player":"Tsung-Che Cheng","team":"BOS","pa":17,"wrc_plus":-5.958,"woba":0.168,"war":-0.172},{"season":2026,"player":"Billy Cook","team":"PIT","pa":30,"wrc_plus":-7.774,"woba":0.161,"war":-0.257},{"season":2026,"player":"Rafael Marchán","team":"PHI","pa":84,"wrc_plus":-10.077,"woba":0.157,"war":-0.186},{"season":2026,"player":"Jase Bowen","team":"SDP","pa":36,"wrc_plus":-10.719,"woba":0.148,"war":-0.231},{"season":2026,"player":"Christian Koss","team":"SFG","pa":20,"wrc_plus":-14.741,"woba":0.144,"war":-0.274},{"season":2026,"player":"Dylan Moore","team":"PHI","pa":15,"wrc_plus":-21.529,"woba":0.14,"war":-0.18},{"season":2026,"player":"Vidal Bruján","team":"NYM","pa":13,"wrc_plus":-21.614,"woba":0.132,"war":-0.097},{"season":2026,"player":"Carson Williams","team":"TBR","pa":33,"wrc_plus":-22.555,"woba":0.139,"war":-0.491},{"season":2026,"player":"Carlos Santana","team":"ARI","pa":26,"wrc_plus":-23.14,"woba":0.137,"war":-0.548},{"season":2026,"player":"Max Kepler","team":"ARI","pa":16,"wrc_plus":-24.534,"woba":0.134,"war":-0.126},{"season":2026,"player":"Jared Oliva","team":"SFG","pa":7,"wrc_plus":-26.045,"woba":0.127,"war":-0.056},{"season":2026,"player":"Ha-Seong Kim","team":"ATL","pa":82,"wrc_plus":-26.308,"woba":0.131,"war":-1.141},{"season":2026,"player":"Oliver Dunn","team":"TBR","pa":12,"wrc_plus":-26.885,"woba":0.132,"war":-0.108},{"season":2026,"player":"Steward Berroa","team":"PHI","pa":7,"wrc_plus":-30.006,"woba":0.127,"war":-0.041},{"season":2026,"player":"Otto Kemp","team":"PHI","pa":27,"wrc_plus":-35.583,"woba":0.119,"war":-0.711},{"season":2026,"player":"Brian Navarreto","team":"MIA","pa":8,"wrc_plus":-36.9,"woba":0.117,"war":-0.04},{"season":2026,"player":"Chad Stevens","team":"COL","pa":34,"wrc_plus":-40.709,"woba":0.129,"war":-0.283},{"season":2026,"player":"Ryan Ritter","team":"COL","pa":7,"wrc_plus":-41.922,"woba":0.127,"war":-0.03},{"season":2026,"player":"Kyler Fedko","team":"MIN","pa":13,"wrc_plus":-43.94,"woba":0.108,"war":-0.22},{"season":2026,"player":"Andy Ibáñez","team":"- - -","pa":26,"wrc_plus":-48.202,"woba":0.095,"war":-0.58},{"season":2026,"player":"Austin Wynns","team":"- - -","pa":57,"wrc_plus":-49.185,"woba":0.101,"war":-0.865},{"season":2026,"player":"Buddy Kennedy","team":"SFG","pa":8,"wrc_plus":-52.752,"woba":0.087,"war":-0.078},{"season":2026,"player":"Greg Jones","team":"MIL","pa":22,"wrc_plus":-56.116,"woba":0.085,"war":-0.384},{"season":2026,"player":"Will Brennan","team":"SFG","pa":23,"wrc_plus":-59.442,"woba":0.078,"war":-0.449},{"season":2026,"player":"Sandy León","team":"ATL","pa":44,"wrc_plus":-59.915,"woba":0.081,"war":-0.511},{"season":2026,"player":"Chuckie Robinson","team":"LAD","pa":26,"wrc_plus":-61.307,"woba":0.078,"war":-0.434},{"season":2026,"player":"Nick Morabito","team":"NYM","pa":12,"wrc_plus":-69.677,"woba":0.061,"war":-0.218},{"season":2026,"player":"Sean Murphy","team":"ATL","pa":14,"wrc_plus":-71.553,"woba":0.064,"war":-0.23},{"season":2026,"player":"Tommy Pham","team":"NYM","pa":14,"wrc_plus":-76.986,"woba":0.05,"war":-0.277},{"season":2026,"player":"Maverick Handley","team":"BAL","pa":1,"wrc_plus":-100,"woba":0,"war":-0.022},{"season":2026,"player":"Michael Siani","team":"BAL","pa":1,"wrc_plus":-100,"woba":0,"war":-0.022},{"season":2026,"player":"Blake Hunt","team":"SDP","pa":3,"wrc_plus":-100,"woba":0,"war":-0.058},{"season":2026,"player":"Davis Wendzel","team":"PIT","pa":4,"wrc_plus":-100,"woba":0,"war":-0.092},{"season":2026,"player":"Ivan Johnson","team":"CIN","pa":4,"wrc_plus":-100,"woba":0,"war":-0.096},{"season":2026,"player":"Trei Cruz","team":"DET","pa":5,"wrc_plus":-100,"woba":0,"war":-0.141},{"season":2026,"player":"Dylan Carlson","team":"CHC","pa":4,"wrc_plus":-100,"woba":0,"war":-0.152},{"season":2026,"player":"Oswaldo Cabrera","team":"NYY","pa":11,"wrc_plus":-100,"woba":0,"war":-0.307},{"season":2026,"player":"César Prieto","team":"STL","pa":17,"wrc_plus":-100,"woba":0,"war":-0.42}]
